library_analyzer/__init__.py
library_analyzer/__main__.py
library_analyzer/cli/__init__.py
library_analyzer/cli/_cli.py
library_analyzer/cli/_json_encoder.py
library_analyzer/cli/_read_and_write_file.py
library_analyzer/cli/_run_all.py
library_analyzer/cli/_run_annotations.py
library_analyzer/cli/_run_api.py
library_analyzer/cli/_run_migrate.py
library_analyzer/cli/_run_usages.py
library_analyzer/cli/_shared_constants.py
library_analyzer/main.py
library_analyzer/processing/__init__.py
library_analyzer/processing/annotations/__init__.py
library_analyzer/processing/annotations/_constants.py
library_analyzer/processing/annotations/_generate_annotations.py
library_analyzer/processing/annotations/_generate_boundary_annotations.py
library_analyzer/processing/annotations/_generate_enum_annotations.py
library_analyzer/processing/annotations/_generate_remove_annotations.py
library_analyzer/processing/annotations/_generate_value_annotations.py
library_analyzer/processing/annotations/_usages_preprocessor.py
library_analyzer/processing/annotations/model/_AnnotationStore.py
library_analyzer/processing/annotations/model/__init__.py
library_analyzer/processing/annotations/model/_annotations.py
library_analyzer/processing/api/__init__.py
library_analyzer/processing/api/_ast_visitor.py
library_analyzer/processing/api/_file_filters.py
library_analyzer/processing/api/_get_api.py
library_analyzer/processing/api/_get_instance_attributes.py
library_analyzer/processing/api/_get_parameter_list.py
library_analyzer/processing/api/_package_metadata.py
library_analyzer/processing/api/documentation_parsing/_AbstractDocumentationParser.py
library_analyzer/processing/api/documentation_parsing/_DefaultDocumentationParser.py
library_analyzer/processing/api/documentation_parsing/_NumpyDocParser.py
library_analyzer/processing/api/documentation_parsing/__init__.py
library_analyzer/processing/api/documentation_parsing/_get_full_docstring.py
library_analyzer/processing/api/model/__init__.py
library_analyzer-0.1.1.dist-info/LICENSE
library_analyzer-0.1.1.dist-info/METADATA
library_analyzer-0.1.1.dist-info/WHEEL
library_analyzer-0.1.1.dist-info/entry_points.txt
library_analyzer-0.1.1.dist-info/RECORD
