Metadata-Version: 2.1
Name: library-analyzer
Version: 0.1.1
Summary: Analysis of Python libraries and code that uses them.
Home-page: https://github.com/Safe-DS/Library-Analyzer
License: MIT
Keywords: static-analysis,library,client-code
Author: Lars Reimann
Author-email: mail@larsreimann.com
Requires-Python: >=3.10,<3.12
Classifier: License :: OSI Approved :: MIT License
Classifier: Programming Language :: Python :: 3
Classifier: Programming Language :: Python :: 3.10
Classifier: Programming Language :: Python :: 3.11
Requires-Dist: astroid (>=2.14.2,<3.0.0)
Requires-Dist: black (>=23.1.0,<24.0.0)
Requires-Dist: levenshtein (>=0.20.9,<0.21.0)
Requires-Dist: numpydoc (>=1.5,<2.0)
Requires-Dist: scipy (>=1.10.1,<2.0.0)
Requires-Dist: spacy (>=3.5.1,<4.0.0)
Project-URL: Documentation, https://library-analyzer.readthedocs.io
Project-URL: Repository, https://github.com/Safe-DS/Library-Analyzer
